oc_dltool-4.0.8.dist-info/licenses/LICENSE
oc_dltoolv2/DeliveryChannels.py
oc_dltoolv2/DeliveryValidations.py
oc_dltoolv2/__init__.py
oc_dltoolv2/__main__.py
oc_dltoolv2/archiver.py
oc_dltoolv2/build_delivery_from_queue.py
oc_dltoolv2/build_steps.py
oc_dltoolv2/db_steps.py
oc_dltoolv2/delivery_artifacts_checker.py
oc_dltoolv2/delivery_attributes.py
oc_dltoolv2/delivery_copyright_appender.py
oc_dltoolv2/delivery_exceptions.py
oc_dltoolv2/delivery_info_decoder.py
oc_dltoolv2/delivery_info_helper.py
oc_dltoolv2/distributives_api_client.py
oc_dltoolv2/dlbuild_worker.py
oc_dltoolv2/enhancements.py
oc_dltoolv2/errors.py
oc_dltoolv2/local_load.py
oc_dltoolv2/notifications.py
oc_dltoolv2/register.py
oc_dltoolv2/releasenotes.py
oc_dltoolv2/resolver.py
oc_dltoolv2/resources.py
oc_dltoolv2/subprocess_wrapper.py
oc_dltoolv2/wrapper.py
oc_dltool-4.0.8.dist-info/METADATA
oc_dltool-4.0.8.dist-info/WHEEL
oc_dltool-4.0.8.dist-info/top_level.txt
oc_dltool-4.0.8.dist-info/RECORD
