Metadata-Version: 2.4
Name: oc-dltool
Version: 4.0.8
Summary: Includes tools for delivery build and release
Requires-Python: >=3.6
License-File: LICENSE
Requires-Dist: oc-cdtapi>=3.18.3
Requires-Dist: oc-checksumsq
Requires-Dist: oc-connections
Requires-Dist: oc-cdt-queue2>=4.1.3
Requires-Dist: oc-dlinterface
Requires-Dist: oc-portal-commons
Requires-Dist: oc-delivery-apps
Requires-Dist: oc-orm-initializator
Requires-Dist: oc-mailer
Requires-Dist: oc-sql-helpers
Requires-Dist: requests
Requires-Dist: oc-logging
Dynamic: description-content-type
Dynamic: license-file
Dynamic: requires-dist
Dynamic: requires-python
Dynamic: summary
